poltergeist/__init__.py
poltergeist/decorator.py
poltergeist/py.typed
poltergeist/result.py
poltergeist-0.10.0.dist-info/LICENSE
poltergeist-0.10.0.dist-info/WHEEL
poltergeist-0.10.0.dist-info/METADATA
poltergeist-0.10.0.dist-info/RECORD
