Metadata-Version: 2.1
Name: poltergeist
Version: 0.10.0
Summary: Rust-like error handling in Python, with type-safety in mind.
Home-page: https://github.com/alexandermalyga/poltergeist
License: MIT
Author: Alexander Malyga
Author-email: alexander@malyga.io
Requires-Python: >=3.10,<4.0
Classifier: Development Status :: 2 - Pre-Alpha
Classifier: Intended Audience :: Developers
Classifier: License :: OSI Approved :: MIT License
Classifier: Programming Language :: Python :: 3
Classifier: Programming Language :: Python :: 3.10
Classifier: Programming Language :: Python :: 3.11
Classifier: Programming Language :: Python :: 3.10
Classifier: Programming Language :: Python :: 3.11
Classifier: Programming Language :: Python :: 3.12
Classifier: Topic :: Software Development :: Libraries :: Python Modules
Classifier: Typing :: Typed
Project-URL: Repository, https://github.com/alexandermalyga/poltergeist
